lib/libhyperloglog.a
include/disjoint_set/ds/disjoint_set.hpp
include/hyperloglog/hll/murmurhash.hpp
include/hyperloglog/hll/hyperloglog.hpp
include/reticula/reticula/temporal_algorithms.hpp
include/reticula/reticula/operations.hpp
include/reticula/reticula/io.hpp
include/reticula/reticula/implicit_event_graphs.hpp
include/reticula/reticula/temporal_clusters.hpp
include/reticula/reticula/implicit_event_graph_components.hpp
include/reticula/reticula/components.hpp
include/reticula/reticula/static_hyperedges.hpp
include/reticula/reticula/temporal_adjacency.hpp
include/reticula/reticula/microcanonical_reference_models.hpp
include/reticula/reticula/type_traits.hpp
include/reticula/reticula/utils.hpp
include/reticula/reticula/network_concepts.hpp
include/reticula/reticula/random_networks.hpp
include/reticula/reticula/static_edges.hpp
include/reticula/reticula/stats.hpp
include/reticula/reticula/algorithms.hpp
include/reticula/reticula/temporal_hyperedges.hpp
include/reticula/reticula/ranges.hpp
include/reticula/reticula/networks.hpp
include/reticula/reticula/distributions.hpp
include/reticula/reticula/temporal_edges.hpp
include/reticula/reticula/reticula.hpp
include/reticula/reticula/intervals.hpp
include/reticula/reticula/generators.hpp
include/indexed_set/indexed_set/indexed_set.hpp
share/disjoint_set/cmake/disjoint_set-config.cmake
share/disjoint_set/cmake/disjoint_set-config-version.cmake
share/disjoint_set/cmake/disjoint_setTargets.cmake
share/hyperloglog/cmake/hyperloglogTargets.cmake
share/hyperloglog/cmake/hyperloglogTargets-release.cmake
share/hyperloglog/cmake/hyperloglog-config.cmake
share/hyperloglog/cmake/hyperloglog-config-version.cmake
share/reticula/cmake/reticula-config-version.cmake
share/reticula/cmake/reticulaTargets.cmake
share/reticula/cmake/reticula-config.cmake
share/indexed_set/cmake/indexed_set-config-version.cmake
share/indexed_set/cmake/indexed_setTargets.cmake
reticula-0.13.0.dist-info/RECORD
reticula-0.13.0.dist-info/METADATA
reticula-0.13.0.dist-info/WHEEL
reticula-0.13.0.dist-info/licenses/LICENSE
