Metadata-Version: 2.1
Name: reticula
Version: 0.13.0
Summary: Analyse temporal network and hypergraphs efficiently.
Keywords: Complex Networks,Networks,network,Graphs,Graph Theory,graph,Temporal Networks,temporal network,Hypergraphs,hypergraph,hyper-graph
Home-page: https://reticula.network/
Author-Email: Arash Badie-Modiri <arashbm@gmail.com>
License: MIT
Classifier: Development Status :: 4 - Beta
Classifier: Intended Audience :: Education
Classifier: Intended Audience :: Science/Research
Classifier: License :: OSI Approved :: MIT License
Classifier: Operating System :: POSIX :: Linux
Classifier: Programming Language :: C++
Classifier: Programming Language :: Python :: 3
Classifier: Programming Language :: Python :: Implementation :: CPython
Classifier: Topic :: Scientific/Engineering
Classifier: Topic :: Scientific/Engineering :: Physics
Classifier: Topic :: Scientific/Engineering :: Mathematics
Classifier: Topic :: Scientific/Engineering :: Information Analysis
Project-URL: Homepage, https://reticula.network/
Project-URL: Documentation, https://docs.reticula.network/
Project-URL: Repository, https://github.com/reticula-network/reticula-python
Project-URL: Bug-tracker, https://github.com/reticula-network/reticula-python/issues
Requires-Python: >=3.10
Provides-Extra: test
Requires-Dist: pytest; extra == "test"
Requires-Dist: hypothesis; extra == "test"
Requires-Dist: pytest-xdist; extra == "test"
